odoo8_addon_l10n_es_account_asset-8.0.2.0.0.99.dev10-py3.6-nspkg.pth
odoo_addons/l10n_es_account_asset/README.rst
odoo_addons/l10n_es_account_asset/__init__.py
odoo_addons/l10n_es_account_asset/__openerp__.py
odoo_addons/l10n_es_account_asset/i18n/ca.po
odoo_addons/l10n_es_account_asset/i18n/cs.po
odoo_addons/l10n_es_account_asset/i18n/de.po
odoo_addons/l10n_es_account_asset/i18n/es.po
odoo_addons/l10n_es_account_asset/i18n/es_CO.po
odoo_addons/l10n_es_account_asset/i18n/fr.po
odoo_addons/l10n_es_account_asset/i18n/fr_BE.po
odoo_addons/l10n_es_account_asset/i18n/gl.po
odoo_addons/l10n_es_account_asset/i18n/hr.po
odoo_addons/l10n_es_account_asset/i18n/l10n_es_account_asset.pot
odoo_addons/l10n_es_account_asset/i18n/pl.po
odoo_addons/l10n_es_account_asset/i18n/pt.po
odoo_addons/l10n_es_account_asset/i18n/pt_BR.po
odoo_addons/l10n_es_account_asset/i18n/ru.po
odoo_addons/l10n_es_account_asset/i18n/sl.po
odoo_addons/l10n_es_account_asset/i18n/sv.po
odoo_addons/l10n_es_account_asset/i18n/vi.po
odoo_addons/l10n_es_account_asset/migrations/8.0.2.0.0/pre-migration.py
odoo_addons/l10n_es_account_asset/models/__init__.py
odoo_addons/l10n_es_account_asset/models/account_asset.py
odoo_addons/l10n_es_account_asset/static/description/icon.png
odoo_addons/l10n_es_account_asset/tests/__init__.py
odoo_addons/l10n_es_account_asset/tests/test_l10n_es_account_asset.py
odoo_addons/l10n_es_account_asset/views/account_asset_view.xml
odoo8_addon_l10n_es_account_asset-8.0.2.0.0.99.dev10.dist-info/METADATA
odoo8_addon_l10n_es_account_asset-8.0.2.0.0.99.dev10.dist-info/WHEEL
odoo8_addon_l10n_es_account_asset-8.0.2.0.0.99.dev10.dist-info/namespace_packages.txt
odoo8_addon_l10n_es_account_asset-8.0.2.0.0.99.dev10.dist-info/top_level.txt
odoo8_addon_l10n_es_account_asset-8.0.2.0.0.99.dev10.dist-info/RECORD
